{
  "metadata": {
    "window_period": "24h",
    "last_period":"5m"
  },
  "trigger": {
    "schedule": {
      "interval": "5m"
    }
  },
  "input": {
    "search": {
      "request": {
        "indices": "log",
        "body": {
          "query": {
            "range": {
              "@timestamp": {
                "gte": "now-{{ctx.metadata.window_period}}"
              }
            }
          },
          "aggs": {
            "periods": {
              "filters": {
                "filters": {
                  "history": {
                    "range": {
                      "@timestamp": {
                        "gte": "now-{{ctx.metadata.window_period}}"
                      }
                    }
                  },
                  "last_period": {
                    "range": {
                      "@timestamp": {
                        "gte": "now-{{ctx.metadata.last_period}}"
                      }
                    }
                  }
                }
              },
              "aggs": {
                "hosts": {
                  "terms": {
                    "field": "host",
                    "size": 10000
                  }
                }
              }
            }
          },
          "size": 0
        }
      }
    }
  },
  "condition": {
    "script": {
      "id": "condition"
    }
  },
  "throttle_period": "5m",
  "actions": {
    "log": {
      "transform": {
      "script": {
        "id":"transform"
      }
    },
      "logging": {
        "text": "Systems not responding in the last {{ctx.metadata.last_period}} minutes:{{#ctx.payload._value}}{{.}}:{{/ctx.payload._value}}"
      }
    }
  }
}
